{
    "instances": {
        "Ælle of Sussex": {
            "label": "Ælle of Sussex",
            "description": "Ælle is recorded in early sources as the first king of the South Saxons, reigning in what is now called Sussex, England, from 477 to perhaps as late as 514. Wikipedia",
            "type": "",
            "Died ": [
                "510 AD"
            ],
            "Children ": [
                "Cissa of Sussex"
            ],
            "People also search for": []
        },
        "Æthelbald of Mercia": {
            "label": "Æthelbald of Mercia",
            "description": "Æthelbald was the King of Mercia, in what is now the English Midlands from 716 until he was killed in 757. Wikipedia",
            "type": "",
            "Died ": [
                "757 AD",
                " Seckington"
            ],
            "People also search for": []
        },
        "Æthelberht II of East Anglia": {
            "label": "Æthelberht II of East Anglia",
            "description": "Æthelberht, also called Saint Ethelbert the King, was an eighth-century saint and a king of East Anglia, the Anglo-Saxon kingdom which today includes the English counties of Norfolk and Suffolk. Wikipedia",
            "type": "Saint",
            "Died ": [
                "May 20",
                " 794 AD"
            ],
            "Parents ": [
                "Æthelred I of East Anglia",
                " Ælfwald of East Anglia"
            ],
            "People also search for": []
        },
        "Æthelwold of East Anglia": {
            "label": "Æthelwold of East Anglia",
            "description": "Æthelwold, also known as Æthelwald or Æþelwald, was a 7th-century king of East Anglia, the long-lived Anglo-Saxon kingdom which today includes the English counties of Norfolk and Suffolk. Wikipedia",
            "type": "King of East Anglia",
            "Died ": [
                "664 AD"
            ],
            "Parents ": [
                "Eni of East Anglia"
            ],
            "Siblings ": [
                "Æthelhere of East Anglia"
            ],
            "People also search for ": [
                "Æthelhere of East Anglia",
                " Eni of East Anglia",
                " Eorpwald of East Anglia",
                " Ealdwulf of East Anglia",
                " Ælfwald of East Anglia",
                " Tytila of East Anglia",
                " Ricberht of East Anglia",
                " Ecgric of East Anglia",
                " Anna of East Anglia",
                " Sigeberht of East Anglia",
                " Wuffa of East Anglia",
                " Wehha of East Anglia",
                " Æthelburh of Faremoutiers",
                " Rædwald of East Anglia",
                " Eadwald of East Anglia",
                " Swithhelm of Essex",
                " Beonna of East Anglia",
                " Æthelred of Mercia",
                " Peada of Mercia",
                " Alberht of East AngliaMore"
            ]
        },
        "Ablai Khan": {
            "label": "Ablai Khan",
            "description": "Wali-ullah Abul-Mansur Khan better known as Ablai Khan was a Kazakh khan of the Middle jüz. Born as Wali-ullah Abul-Mansur Khan, Ablai Khan belonged to the senior branch of descendants of the 15th century founder of the Kazakh state, Janybek Khan. Wikipedia",
            "type": "",
            "Born ": "May 23, 1711, Turkistan, Kazakhstan",
            "Died ": "May 23, 1781",
            "People also search for": []
        },
        "Aktisanes": {
            "label": "Aktisanes",
            "description": "Aktisanes is a Nubian king who is mentioned by the Greek historian Hecataeus of Abdera. He is perhaps identical with Menmaatre-Setepenamun Gatisen known from Nubian sources. Wikipedia",
            "type": "",
            "People also search for ": [
                "Aryamani",
                " Amanineteyerike",
                " Harsiotef",
                " Akhraten",
                " Talakhamani",
                " Malewiebamani",
                " Analmaye",
                " Arqamani",
                " Nastasen",
                " Malonaqen",
                " Shorkaror",
                " Nasakhma",
                " Aramatle-qo",
                " Sabrakamani",
                " SiaspiqaMore"
            ]
        },
        "Aldfrith of Northumbria": {
            "label": "Aldfrith of Northumbria",
            "description": "Aldfrith was king of Northumbria from 685 until his death. He is described by early writers such as Bede, Alcuin and Stephen of Ripon as a man of great learning. Some of his works and some letters written to him survive. Wikipedia",
            "type": "",
            "Died ": [
                "December 14",
                " 705 AD",
                " Driffield",
                " United Kingdom"
            ],
            "Spouse ": [
                "Cuthburh"
            ],
            "Parents ": [
                "Oswiu of Northumbria"
            ],
            "Siblings ": [
                "Ecgfrith of Northumbria"
            ],
            "Children ": [
                "Osred I of Northumbria",
                " Osric of Northumbria",
                " Osana"
            ],
            "People also search for": []
        },
        "Al-Muzaffar Umar": {
            "label": "Al-Muzaffar Umar",
            "description": "Al-Muzaffar Taqi al-Din Umar was the Ayyubid prince of Hama from 1179 to 1191 and a general of Saladin. He was the son of Saladin's brother Nur al-Din Shahanshah and brother of Farrukh Shah of Baalbek. Wikipedia",
            "type": "",
            "Born ": [
                "Syria"
            ],
            "People also search for ": [
                "As-Salih Ismail",
                " Al-Mansur Nasir al-Din Muhammad",
                " Al-Ashraf Musa",
                " Emir of Homs",
                " Al-Ashraf",
                " Al-Mu'azzam",
                " An-Nasir Yusuf",
                " Al-Mansur Ibrahim",
                " Al-Adil II",
                " Al-Aziz Uthman",
                " An-Nasir Dawud",
                " Al-Afdal Muhammad",
                " Turan-Shah",
                " Al-Muazzam Turanshah",
                " Al-Mujahid",
                " Al-Afdal ibn Salah ad-Din",
                " Najm ad-Din Ayyub",
                " Al-Ashraf Musa",
                " Sultan of Egypt",
                " Al-Adil I",
                " Al-Zahir Ghazi",
                " As-Salih AyyubMore"
            ]
        },
        "Apollodotus II": {
            "label": "Apollodotus II",
            "description": "Apollodotus II, was an Indo-Greek king who ruled in the western and eastern parts of Punjab. Bopearachchi dates him to circa 80–65 BCE, and R. C. Senior to circa 85–65 BCE. Wikipedia",
            "type": "",
            "Born ": [
                "80 BC"
            ],
            "Died ": [
                "65 BC"
            ],
            "People also search for": []
        },
        "Archduke Eugen of Austria": {
            "label": "Archduke Eugen of Austria",
            "description": "Archduke Eugen Ferdinand Pius Bernhard Felix Maria of Austria-Teschen was an Archduke of Austria and a Prince of Hungary and Bohemia. He was the last Grand Master of the Teutonic Knights from the Habsburg dynasty. Wikipedia",
            "type": "",
            "Born ": "June 21, 1863, Židlochovice, Czech Republic",
            "Died ": "December 30, 1954, Merano, Italy",
            "Parents ": [
                "Archduke Karl Ferdinand of Austria",
                " Archduchess Elisabeth Franziska of Austria"
            ],
            "People also search for": []
        },
        "Baskakeren": {
            "label": "Baskakeren",
            "description": "Baskakeren was a king of Kush. He was likely a son of King Malewiebamani and the younger brother of King Amanineteyerike. He succeeded King Amanineteyerike to the throne.\nBaskakeren is so far only known from his small pyramid in Nuri. Wikipedia",
            "type": "",
            "Parents ": [
                "Malewiebamani"
            ],
            "People also search for ": [
                "Amanineteyerike",
                " Malewiebamani",
                " Talakhamani",
                " Harsiotef",
                " Nasakhma",
                " Malonaqen",
                " Amanikhabale",
                " Akhraten",
                " Atlanersa",
                " Siaspiqa",
                " Analmaye",
                " Aryamani",
                " Aramatle-qo",
                " Nastasen",
                " AnlamaniMore"
            ]
        },
        "Axayacatl": {
            "label": "Axayacatl",
            "description": "Axayacatl of the Postclassic Mesoamerican Aztec Empire and city of Tenochtitlan, who reigned from 1469 to 1481.\nHe is chiefly remembered for subjugating Tlatelolco, Tenochtitlan's sister city, in 1473. Wikipedia",
            "type": "",
            "Died ": [
                "1481"
            ],
            "Children ": [
                "Moctezuma II",
                " Cuitláhuac"
            ],
            "Parents ": [
                "Atotoztli II",
                " Tezozomoc"
            ],
            "People also search for": []
        },
        "Bindusara": {
            "label": "Bindusara",
            "description": "Bindusara Maurya was emperor of the Maurya Empire from 298 BC – 272 BC. During his reign, the empire expanded southwards. He had two well-known sons, Susima and Ashoka, who were the viceroys of Takshashila and Ujjain. Wikipedia",
            "type": "",
            "Born ": [
                "320 BC",
                " India"
            ],
            "Died ": [
                "272 BC"
            ],
            "Parents ": [
                "Durdhara",
                " Chandragupta Maurya"
            ],
            "Children ": [
                "Ashoka",
                " Susima",
                " Vitashoka"
            ],
            "People also search for": []
        },
        "Borandukht": {
            "label": "Borandukht",
            "description": "Boran or Poran, or more correctly Burandokht or Purandokht, was the daughter of the King Khosrau II. She was one of only two women on the throne of the Sasanian Empire. Wikipedia",
            "type": "",
            "Born ": [
                "590 AD"
            ],
            "Died ": [
                "628 AD",
                " Ctesiphon",
                " Iraq"
            ],
            "Parents ": [
                "Khosrau II"
            ],
            "Siblings ": [
                "Azarmidokht"
            ],
            "People also search for": []
        },
        "Branimir of Croatia": {
            "label": "Branimir of Croatia",
            "description": "Branimir was a ruler of the Duchy of Croatia who reigned as knez from 879 to 892. His country recevied papal recognition as a state from Pope John VIII on 7 June 879. Wikipedia",
            "type": "",
            "Died ": [
                "892 AD"
            ],
            "People also search for": []
        },
        "Cissa of Sussex": {
            "label": "Cissa of Sussex",
            "description": "Cissa was part of an Anglo-Saxon invasion force that landed in three ships at a place called Cymensora in 477AD. The invasion was led by Cissa's father Ælle and included his two brothers. They are said to have fought against the local Britons. Wikipedia",
            "type": "",
            "Parents ": [
                "Ælle of Sussex"
            ],
            "People also search for": []
        },
        "Constantine Mavrocordatos": {
            "label": "Constantine Mavrocordatos",
            "description": "Constantine Mavrocordatos was a Greek noble who served as Prince of Wallachia and Prince of Moldavia at several intervals. Wikipedia",
            "type": "",
            "Born ": "February 27, 1711, Constantinople, Turkey",
            "Died ": "November 23, 1769, Wallachia, Romania",
            "Parents ": [
                "Nicholas Mavrocordatos"
            ],
            "People also search for": []
        },
        "Cynethryth": {
            "label": "Cynethryth",
            "description": "Cynethryth was a Queen of Mercia and wife of King Offa of Mercia and mother of King Ecgfrith of Mercia. Cynethryth is the only Anglo-Saxon Queen consort in whose name coinage was definitely issued. Wikipedia",
            "type": "",
            "Spouse ": [
                "Offa of Mercia"
            ],
            "Children ": [
                "Eadburh",
                " Ecgfrith of Mercia",
                " Ælfflæd of Mercia"
            ],
            "People also search for": []
        },
        "Daher el-Omar": {
            "label": "Daher el-Omar",
            "description": "Daher el-Omar was the autonomous Arab ruler of the Galilee region during the mid-18th century. The founder of modern Haifa, he fortified many cities, among them Acre. Wikipedia",
            "type": "",
            "Born ": [
                "1690",
                " Tiberias",
                " Israel"
            ],
            "Died ": "August 21, 1775, Acre, Israel",
            "People also search for": []
        },
        "Dietrich I von Hengebach": {
            "label": "Dietrich I von Hengebach",
            "description": "Dietrich I von Hengebach was the Archbishop of Cologne. He was elected in 1208. He supported Otto of the House of Welf as Holy Roman Emperor and was excommunicated in 1212 by Innocent III. Wikipedia",
            "type": "",
            "Born ": [
                "1150"
            ],
            "People also search for": []
        },
        "Ecgric of East Anglia": {
            "label": "Ecgric of East Anglia",
            "description": "Ecgric was a king of East Anglia, the independent Anglo-Saxon kingdom that today includes the English counties of Norfolk and Suffolk. Wikipedia",
            "type": "",
            "Died ": [
                "635 AD"
            ],
            "Children ": [
                "Ealdwulf of East Anglia"
            ],
            "People also search for ": [
                "Sigeberht of East Anglia",
                " Eorpwald of East Anglia",
                " Æthelhere of East Anglia",
                " Ealdwulf of East Anglia",
                " Æthelwold of East Anglia",
                " Eni of East Anglia",
                " Ricberht of East Anglia",
                " Ælfwald of East Anglia",
                " Tytila of East Anglia",
                " Wehha of East Anglia",
                " Wuffa of East Anglia",
                " Anna of East Anglia",
                " Eadwald of East Anglia",
                " Osric of Deira",
                " Beonna of East Anglia",
                " Eanfrith of Bernicia",
                " Rædwald of East Anglia",
                " Felix of Burgundy",
                " Coenred of Mercia",
                " Ceolwulf I of MerciaMore"
            ]
        },
        "Basarab I of Wallachia": {
            "label": "Basarab I of Wallachia",
            "description": "Basarab I the Founder Ivanco Basarab according to a medieval Serbian document was voivode or prince of Wallachia. Wikipedia",
            "type": "",
            "Died ": [
                "1352",
                " Câmpulung",
                " Romania"
            ],
            "Parents ": [
                "Thocomerius"
            ],
            "Children ": [
                "Nicholas Alexander of Wallachia",
                " Theodora of Wallachia"
            ],
            "People also search for": []
        },
        "Archebius": {
            "label": "Archebius",
            "description": "Archebius Dikaios Nikephoros was an Indo-Greek king who ruled in the area of Taxila. Osmund Bopearachchi dates him to circa 90–80 BCE, and R. C. Senior to about the same period. Wikipedia",
            "type": "",
            "People also search for ": [
                "Heliokles II",
                " Philoxenus Anicetus",
                " Strato I",
                " Diomedes Soter",
                " Zoilos I",
                " Maues",
                " Amyntas Nikator",
                " Apollodotus II",
                " Lysias Anicetus",
                " Demetrios III",
                " Hippostratos",
                " Polyxenos Epiphanes Soter",
                " Antialcidas",
                " Apollodotus I",
                " King Telephos",
                " Zoilos II",
                " Dionysios Soter",
                " Epander",
                " Antimachus I",
                " Antimachus IIMore"
            ]
        },
        "Dionysios Soter": {
            "label": "Dionysios Soter",
            "description": "Dionysios Soter was an Indo-Greek king in the area of eastern Punjab. Wikipedia",
            "type": "",
            "People also search for ": [
                "Zoilos II",
                " Hippostratos",
                " Polyxenos Epiphanes Soter",
                " King Telephos",
                " Apollophanes",
                " Antimachus II",
                " Strato I",
                " Diomedes Soter",
                " Theophilos",
                " Archebius",
                " Heliokles II",
                " Philoxenus Anicetus",
                " Demetrios III",
                " Antimachus I",
                " Amyntas Nikator",
                " Apollodotus II",
                " Peukolaos",
                " Lysias Anicetus",
                " Apollodotus I",
                " PantaleonMore"
            ]
        },
        "Emperor Chūkyō": {
            "label": "Emperor Chūkyō",
            "description": "Emperor Chūkyō was the 85th emperor of Japan, according to the traditional order of succession. His reign spanned only months in 1221, and he was not officially listed amongst the emperors until 1870 ... Wikipedia",
            "type": "",
            "Born ": "October 30, 1218",
            "Died ": "June 18, 1234",
            "Parents ": [
                "Emperor Juntoku"
            ],
            "People also search for": []
        },
        "Empress Kōgyoku": {
            "label": "Empress Kōgyoku",
            "description": "Empress Kōgyoku, also known as Empress Saimei, was the 35th and 37th monarch of Japan, according to the traditional order of succession.\nKōgyoku's reign spanned the years from 642–645. Her reign as Saimei encompassed 655–661. Wikipedia",
            "type": "",
            "Born ": [
                "August 7",
                " 594 AD"
            ],
            "Died ": [
                "August 24",
                " 661 AD"
            ],
            "Spouse ": [
                "Emperor Jomei"
            ],
            "Children ": [
                "Emperor Tenji",
                " Emperor Tenmu"
            ],
            "People also search for": []
        },
        "Emperor Rokujō": {
            "label": "Emperor Rokujō",
            "description": "Emperor Rokujō was the 79th emperor of Japan, according to the traditional order of succession. His reign spanned the years from 1165 through 1168. Wikipedia",
            "type": "",
            "Born ": "December 28, 1164",
            "Died ": "August 23, 1176",
            "Parents ": [
                "Emperor Nijō"
            ],
            "People also search for": []
        },
        "Emperor Toba": {
            "label": "Emperor Toba",
            "description": "Emperor Toba was the 74th emperor of Japan, according to the traditional order of succession.\nToba's reign spanned the years from 1107 through 1123. Wikipedia",
            "type": "",
            "Born ": "February 24, 1103",
            "Died ": "July 20, 1156",
            "Parents ": [
                "Emperor Horikawa"
            ],
            "Children ": [
                "Emperor Sutoku",
                " Emperor Go-Shirakawa"
            ],
            "People also search for": []
        },
        "Empress Meishō": {
            "label": "Empress Meishō",
            "description": "Empress Meishō was the 109th Imperial ruler of Japan, according to the traditional order of succession.\nMeishō's reign spanned the years from 1629 to 1643.\nIn the history of Japan, Meishō was the seventh of eight women to become empress regnant. Wikipedia",
            "type": "",
            "Born ": "January 9, 1624",
            "Died ": "December 4, 1696",
            "Parents ": [
                "Emperor Go-Mizunoo"
            ],
            "People also search for": []
        },
        "Enlil-bani": {
            "label": "Enlil-bani",
            "description": "Enlil-bāni, ca. 1798 BC – 1775 BC or 1860-1837 BC, was the 10th king of the 1st Dynasty of Isin and reigned 24 years according to the Ur-Isin kinglist. He is best known for the legendary and perhaps apocryphal manner of his ascendancy. Wikipedia",
            "type": "",
            "People also search for ": [
                "Erra-imitti",
                " Iddin-Dagan",
                " Lipit-Enlil",
                " Damiq-ilishu",
                " Bur-Suen",
                " Ur-Ninurta",
                " Ishme-Dagan",
                " Suen-magir",
                " Shu-Ilishu",
                " Ur-du-kuga",
                " Iter-pisha",
                " Ishbi-Erra",
                " Nur-Adad",
                " Zambiya",
                " Abisare",
                " Gungunum",
                " Sin-Iddinam",
                " Lipit-Ishtar",
                " Warad-Sin",
                " SumuelMore"
            ]
        },
        "Ferdinand Kettler": {
            "label": "Ferdinand Kettler",
            "description": "Ferdinand Kettler was Duke of Courland and Semigallia from 1730 to 1737. Ferdinand was the son of Jacob Kettler and Louise Charlotte of Brandenburg. Married in 1730 to Johanna Magdalene of Saxe-Weissenfels. Wikipedia",
            "type": "",
            "Born ": "November 1, 1655, Jelgava, Latvia",
            "Died ": "May 4, 1737, Gdańsk, Poland",
            "Parents ": [
                "Jacob Kettler",
                " Margravine Louise Charlotte of Brandenburg"
            ],
            "People also search for": []
        },
        "Friedrich Kettler": {
            "label": "Friedrich Kettler",
            "description": "Friedrich Kettler was Duke of Courland from 1587 to 1642.\nHe was the son of Gotthard Kettler, the first Duke of Courland. Wikipedia",
            "type": "",
            "Born ": "November 25, 1569, Jelgava, Latvia",
            "Died ": "August 17, 1642, Jelgava, Latvia",
            "Spouse ": [
                "Elisabeth Magdalena of Pomerania"
            ],
            "Parents ": [
                "Anna of Mecklenburg",
                " Gotthard Kettler"
            ],
            "People also search for": []
        },
        "Gajah Mada": {
            "label": "Gajah Mada",
            "description": "Gajah Mada was, according to Javanese old manuscripts, poems and mythology, a powerful military leader and mahapatih or prime minister of the Majapahit Empire, credited with bringing the empire to its peak of glory. Wikipedia",
            "type": "",
            "Died ": [
                "1364"
            ],
            "People also search for": []
        },
        "Gavril Radomir of Bulgaria": {
            "label": "Gavril Radomir of Bulgaria",
            "description": "Gavril Radomir, normally rendered as Gabriel Radomir in English and Gavriil Romanos in Greek, was the ruler of the First Bulgarian Empire from October 1014 to August or September 1015. He was the son of Samuel of Bulgaria. Wikipedia",
            "type": "",
            "Died ": [
                "1015"
            ],
            "Spouse ": [
                "Irene of Larissa"
            ],
            "Children ": [
                "Peter Delyan"
            ],
            "Parents ": [
                "Kosara",
                " Agatha",
                " wife of Samuil",
                " Samuel of Bulgaria"
            ],
            "People also search for": []
        },
        "Gebhard Truchsess von Waldburg": {
            "label": "Gebhard Truchsess von Waldburg",
            "description": "Gebhard Truchsess von Waldburg was Archbishop-Elector of Cologne. After pursuing an ecclesiastical career, he won a close election in the Cathedral chapter of Cologne over Ernst of Bavaria. Wikipedia",
            "type": "",
            "Born ": "November 10, 1547, Überlingen, Germany",
            "Died ": "May 31, 1601, Strasbourg, France",
            "People also search for": []
        },
        "Gediminas": {
            "label": "Gediminas",
            "description": "Gediminas was Grand Duke of Lithuania from 1315 or 1316 until his death. He is credited with founding this political entity and expanding its territory which, at the time of his death, spanned the area ranging from the Baltic Sea to the Black Sea. Wikipedia",
            "type": "",
            "Born ": [
                "1275"
            ],
            "Died ": [
                "December 1341",
                " Vilnius",
                " Lithuania"
            ],
            "Full name ": [
                "Gediminas"
            ],
            "Children ": [
                "Algirdas",
                " Kęstutis",
                " Liubartas",
                " Jaunutis",
                " Aldona of Lithuania",
                " Narimantas",
                " Karijotas",
                " Manvydas",
                " Elžbieta Gediminaitė",
                " Aigusta Anastasia of Lithuania",
                " EufemijaMore"
            ],
            "Spouse ": [
                "Vindemunda",
                " Olga Smolenskietė"
            ],
            "Siblings ": [
                "Vytenis",
                " Fiodor of Kiev"
            ],
            "People also search for": []
        },
        "Iter-pisha": {
            "label": "Iter-pisha",
            "description": "Iter-piša, inscribed in cuneiform as i-te-er-pi/pi4-ša and meaning \"Her command is surpassing\", ca. 1769–1767 BC or ca. 1833–1831 BC, was the 12th king of Isin during the Old Babylonian period. Wikipedia",
            "type": "",
            "People also search for ": [
                "Lipit-Enlil",
                " Ur-du-kuga",
                " Suen-magir",
                " Damiq-ilishu",
                " Zambiya",
                " Shu-Ilishu",
                " Bur-Suen",
                " Silli-Adad",
                " Sin-Iqisham",
                " Ur-Ninurta",
                " Erra-imitti",
                " Enlil-bani",
                " Sin-Eribam",
                " Abisare",
                " Iddin-Dagan",
                " Warad-Sin",
                " Ishme-Dagan",
                " Nur-Adad",
                " Kudur-MabukMore"
            ]
        },
        "Ithobaal I": {
            "label": "Ithobaal I",
            "description": "Ithobaal I was a king of Tyre who founded a new dynasty. During his reign, Tyre expanded its power on the mainland, making all of Phoenicia its territory as far north as Beirut, including Sidon, and even a part of the island of Cyprus. Wikipedia",
            "type": "",
            "Born ": [
                "915 BC"
            ],
            "Children ": [
                "Jezebel",
                " Baal-Eser II"
            ],
            "People also search for": []
        },
        "Jehoash of Judah": {
            "label": "Jehoash of Judah",
            "description": "Jehoash or Joas, sometimes written Joash or Joás, was the eighth king of Judah since his fourth great-grandfather Rehoboam, and the sole surviving son of Ahaziah. His mother was Zibiah of Beersheba. Wikipedia",
            "type": "",
            "Born ": [
                "Jerusalem",
                " Israel"
            ],
            "Died ": [
                "Jerusalem",
                " Israel"
            ],
            "Parents ": [
                "Ahaziah of Judah"
            ],
            "Children ": [
                "Amaziah of Judah"
            ],
            "People also search for": []
        },
        "Jovan Vladimir": {
            "label": "Jovan Vladimir",
            "description": "Jovan Vladimir or John Vladimir was the ruler of Duklja, the most powerful Serbian principality of the time, from around 1000 to 1016. He ruled during the protracted war between the Byzantine Empire and the First Bulgarian Empire. Wikipedia",
            "type": "",
            "Died ": "May 22, 1016, Prespa",
            "Spouse ": [
                "Theodora Kosara of Bulgaria"
            ],
            "Parents ": [
                "Petrislav of Duklja"
            ],
            "People also search for": []
        },
        "K'inich Janaab' Pakal": {
            "label": "K'inich Janaab' Pakal",
            "description": "K'inich Janaab' Pakal was ruler of the Maya polity of Palenque in the Late Classic period of pre-Columbian Mesoamerican chronology. Wikipedia",
            "type": "",
            "Born ": [
                "March 23",
                " 603 AD"
            ],
            "Died ": [
                "August 28",
                " 683 AD"
            ],
            "Parents ": [
                "Sak K'uk'"
            ],
            "Children ": [
                "K'inich Kan B'alam II",
                " K'inich K'an Joy Chitam II"
            ],
            "People also search for": []
        },
        "Kanishka II": {
            "label": "Kanishka II",
            "description": "Kanishka II was one of the emperors of the Kushan Empire from around 225–245 CE. He succeeded Vasudeva I who is considered to be the last great Kushan emperor. It is likely he lost part of his empire to the Kushano-Sassanians. Wikipedia",
            "type": "",
            "People also search for": []
        },
        "King Nicias": {
            "label": "King Nicias",
            "description": "Nicias was an Indo-Greek king who ruled in the Paropamisade. Most of his relatively few coins have been found in northern Pakistan, indicating that he ruled a smaller principate around the lower Kabul valley. Wikipedia",
            "type": "",
            "People also search for ": [
                "Diomedes Soter",
                " Philoxenus Anicetus",
                " Polyxenos Epiphanes Soter",
                " Theophilos",
                " Amyntas Nikator",
                " Epander",
                " Dionysios Soter",
                " Antimachus II",
                " Lysias Anicetus",
                " King Telephos",
                " Demetrios III",
                " Peukolaos",
                " Archebius",
                " Demetrius II of India",
                " Heliokles II",
                " Strato I",
                " Agathokleia",
                " Zoilos II",
                " Zoilos I",
                " ApollophanesMore"
            ]
        },
        "Kormisosh of Bulgaria": {
            "label": "Kormisosh of Bulgaria",
            "description": "Kormisosh was a ruler of Bulgaria during the 8th century.\nThe Namelist of Bulgarian Rulers states that he belonged to the Ukil clan and ruled for 17 years. Wikipedia",
            "type": "",
            "People also search for": []
        },
        "Kumaragupta I": {
            "label": "Kumaragupta I",
            "description": "Kumaragupta I was a ruler of the Gupta Empire in 415–455 CE. Like his father and predecessor, Chandragupta II, Kumaragupta was an able ruler. Wikipedia",
            "type": "",
            "Parents ": [
                "Chandragupta II"
            ],
            "Children ": [
                "Purugupta"
            ],
            "People also search for": []
        },
        "Enno II, Count of East Frisia": {
            "label": "Enno II, Count of East Frisia",
            "description": "Enno II of East Frisia was the son of Edzard I of East Frisia. In 1528 he became count of East Frisia. For most of his life he ruled together with Johan I of East Frisia, who remained Catholic, while Enno was Lutheran. Wikipedia",
            "type": "",
            "Born ": [
                "1505"
            ],
            "Died ": "September 24, 1540, Emden, Germany",
            "Spouse ": [
                "Anna of Oldenburg"
            ],
            "Parents ": [
                "Edzard I",
                " Count of East Frisia"
            ],
            "Children ": [
                "Edzard II",
                " Count of East Frisia",
                " Johan II of East Frisia"
            ],
            "People also search for": []
        },
        "Leopold II, Prince of Lippe": {
            "label": "Leopold II, Prince of Lippe",
            "description": "Leopold II of Lippe was the sovereign of the Principality of Lippe. He succeeded to the throne in 1802, and in 1820 he assumed control of the government from his mother who had been acting as regent due to his youth at accession. Wikipedia",
            "type": "",
            "Born ": "November 6, 1796, Detmold, Germany",
            "Died ": "January 1, 1851, Detmold, Germany",
            "Children ": [
                "Leopold III",
                " Prince of Lippe",
                " Woldemar",
                " Prince of Lippe",
                " Alexander",
                " Prince of Lippe"
            ],
            "Parents ": [
                "Princess Pauline of Anhalt-Bernburg",
                " Leopold I",
                " Prince of Lippe"
            ],
            "People also search for": []
        },
        "Meritaten": {
            "label": "Meritaten",
            "description": "Meritaten also spelled Merytaten or Meryetaten was an ancient Egyptian queen of the eighteenth dynasty, who held the position of Great Royal Wife to Pharaoh Smenkhkare, who may have been a brother or son of Akhenaten. Wikipedia",
            "type": "",
            "Born ": [
                "Thebes",
                " Egypt"
            ],
            "Spouse ": [
                "Smenkhkare"
            ],
            "Siblings ": [
                "Ankhesenamun",
                " Meketaten",
                " Neferneferuaten Tasherit",
                " Neferneferure",
                " Setepenre"
            ],
            "Parents ": [
                "Akhenaten",
                " Nefertiti"
            ],
            "Children ": [
                "Meritaten Tasherit"
            ],
            "People also search for": []
        },
        "Emperor Go-Tsuchimikado": {
            "label": "Emperor Go-Tsuchimikado",
            "description": "Emperor Go-Tsuchimikado was the 103rd emperor of Japan, according to the traditional order of succession. His reign spanned the years from 1464 through 1500. Wikipedia",
            "type": "",
            "Born ": "July 3, 1442",
            "Died ": "October 21, 1500",
            "People also search for": []
        },
        "Mircea I of Wallachia": {
            "label": "Mircea I of Wallachia",
            "description": "Mircea the Elder was ruler of Wallachia from 1386 until his death. The byname \"elder\" was given to him after his death in order to distinguish him from his grandson Mircea II. Wikipedia",
            "type": "",
            "Born ": [
                "1355",
                " Wallachia",
                " Romania"
            ],
            "Died ": "January 31, 1418, Wallachia, Romania",
            "Spouse ": [
                "Doamna Mara"
            ],
            "Children ": [
                "Vlad II Dracul",
                " Alexander I Aldea",
                " Michael I of Wallachia",
                " Radu II of Wallachia"
            ],
            "Parents ": [
                "Radu I of Wallachia",
                " Lady Calinica"
            ],
            "Siblings ": [
                "Dan I of Wallachia"
            ],
            "People also search for": []
        },
        "Mindaugas": {
            "label": "Mindaugas",
            "description": "Mindaugas was the first known Grand Duke of Lithuania and the only King of Lithuania. Little is known of his origins, early life, or rise to power; he is mentioned in a 1219 treaty as an elder duke, and in 1236 as the leader of all the Lithuanians. Wikipedia",
            "type": "",
            "Born ": [
                "1203",
                " Lithuania"
            ],
            "Full name ": [
                "Mindaugas"
            ],
            "Assassinated ": "September 12, 1263, Aglona, Latvia",
            "Spouse ": [
                "Morta"
            ],
            "Parents ": [
                "Ryngold"
            ],
            "Children ": [
                "Vaišvilkas",
                " Daumantas of Pskov"
            ],
            "People also search for": []
        },
        "Lobengula": {
            "label": "Lobengula",
            "description": "Lobengula Khumalo was the second and last king of the Ndebele people, usually called Matabele in English. Wikipedia",
            "type": "",
            "Born ": [
                "1845",
                " Matabeleland",
                " Zimbabwe"
            ],
            "Died ": "January 23, 1894, Matabeleland, Zimbabwe",
            "Parents ": [
                "Mzilikazi",
                " Princess of the Swazi House of Sobhuza I"
            ],
            "Children ": [
                "Njube",
                " Sidojiwa",
                " Nguboyenja",
                " Mpezeni"
            ],
            "People also search for": []
        },
        "Mohammed Adil Shah": {
            "label": "Mohammed Adil Shah",
            "description": "Muhammad Adil Shah was the ruler of Bijapur, ascending the throne in 1627 at the comparatively young age of sixteen years. This was accomplished with the help of two Bijapuri nobles – Daulat Khan and Mirza Muhammad Amin Lari. Wikipedia",
            "type": "",
            "Born ": [
                "1601",
                " Bijapur",
                " India"
            ],
            "Died ": "November 4, 1656",
            "Parents ": [
                "Ibrahim Adil Shah II"
            ],
            "Children ": [
                "Ali Adil Shah II"
            ],
            "Structures ": [
                "Gol Gumbaz"
            ],
            "People also search for ": [
                "Ibrahim Adil Shah II",
                " Ali Adil Shah II",
                " Yusuf Adil Shah",
                " Sikandar Adil Shah",
                " Ali Adil Shah I",
                " Ibrahim Adil Shah I",
                " Ismail Adil ShahMore"
            ]
        },
        "Mohammed ash-Sheikh": {
            "label": "Mohammed ash-Sheikh",
            "description": "Mawlay Mohammed ash-Sheikh ash Sharif al-Hassani al-Drawi at-Tagmaderti was the first sultan of the Saadi dynasty ruling over Morocco. \"Al-Drawi at-Tagmadert\" means the man from the Draa river valley, from Tagmadert. Wikipedia",
            "type": "",
            "Died ": "October 23, 1557",
            "Children ": [
                "Ahmad al-Mansur",
                " Abdallah al-Ghalib",
                " Abu Marwan Abd al-Malik I Saadi"
            ],
            "People also search for ": [
                "Abdallah al-Ghalib",
                " Abu Marwan Abd al-Malik I Saadi",
                " Ahmad al-Mansur",
                " Abu Abdallah Mohammed II Saadi",
                " Ali Abu Hassun",
                " Ali ibn Muhammad",
                " Ahmed al-Hiba",
                " Yahya ibn Yahya",
                " Yahya ibn Al-Qassim",
                " Muhammad ibn Idris",
                " Al-Hasan ibn Kannun",
                " Ali ibn Umar",
                " Abu Abdallah al-Qaim",
                " Yahya ibn Idris ibn Umar",
                " Al-Hajjam al-Hasan ibn Muhammad ibn al-Qassim",
                " Mohammed ben Abdallah",
                " Yahya ibn Muhammad",
                " Ahmad al-Araj",
                " Abu l-Aish Ahmad",
                " Ibrahim ibn TashfinMore"
            ]
        },
        "Mussius Aemilianus": {
            "label": "Mussius Aemilianus",
            "description": "Lucius Mussius Aemilianus was a Roman usurper.\nMussius Aemilianus probably was of Italian stock. He was an officer in the Roman army under Philip the Arab and Valerian. Under the latter he became praefect of Egypt. Wikipedia",
            "type": "",
            "People also search for": []
        },
        "Muwenda Mutebi II of Buganda": {
            "label": "Muwenda Mutebi II of Buganda",
            "description": "Ronald Edward Frederick Kimera Muwenda Mutebi II is the reigning Kabaka of the Kingdom of Buganda, a kingdom in modern-day Uganda. He is the thirty-sixth Kabaka of Buganda. Wikipedia",
            "type": "",
            "Born ": "April 13, 1955 (age 58), Mengo, Uganda",
            "Spouse ": [
                "Queen Sylvia of Buganda (m. 1999)"
            ],
            "Education ": [
                "Magdalene College",
                " Cambridge"
            ],
            "Parents ": [
                "Mutesa II of Buganda"
            ],
            "Siblings ": [
                "Daudi Kintu Wasajja"
            ],
            "People also search for": []
        },
        "Nabû-mukin-apli": {
            "label": "Nabû-mukin-apli",
            "description": "Nabû-mukin-apli, typically inscribed dAG-DU-A, “Nabû establisher of a legitimate heir,” 978 – 943 BC, founded Babylon’s 8th dynasty, the so-called Dynasty of E, and ruled for 36 years. Wikipedia",
            "type": "",
            "People also search for ": [
                "Nabu-apla-iddina",
                " Marduk-zakir-shumi I",
                " Nabu-shuma-ukin I",
                " Simbar-shipak",
                " Mar-biti-apla-usur",
                " Marduk-nadin-ahhe",
                " Nabu-mukin-zeri",
                " Mar-biti-ahhe-iddina",
                " Adad-shuma-usur",
                " Ninurta-kudurri-usur II",
                " Adad-apla-iddina",
                " Marduk-apla-iddina I",
                " Agum II",
                " Ashur-nadin-shumi",
                " Kadashman-Enlil II",
                " Ninurta-kudurri-usur I",
                " Agum III",
                " Kadashman-Turgu",
                " Marduk-balassu-iqbi",
                " Enlil-nadin-shumiMore"
            ],
            "See results about": []
        },
        "Nabonassar": {
            "label": "Nabonassar",
            "description": "Nabû-nāṣir, inscribed in cuneiform as dAG-PAB or dAG-ŠEŠ-ir, Greek Ναβονάσσαρος from whence comes \"Nabonassar\", and meaning \"Nabû protector\", was the king of Babylon 747–732 BC, beginning a new era characterized by the systematic maintenance of ... Wikipedia",
            "type": "",
            "Died ": [
                "734 BC"
            ],
            "People also search for": []
        },
        "Nabu-mukin-zeri": {
            "label": "Nabu-mukin-zeri",
            "description": "Nabû-mukin-zēri, inscribed mdAG-DU-NUMUN, also known as Mukin-zēri, was the king of Babylon 731–729 BC. The Ptolemaic Canon gives his name as Χινζηρος. Wikipedia",
            "type": "",
            "People also search for ": [
                "Nabû-mukin-apli",
                " Ashur-nadin-shumi",
                " Nabu-suma-ukin II",
                " Bel-ibni",
                " Nabonassar",
                " Nabu-shuma-ukin I",
                " Adad-apla-iddina",
                " Mushezib-Marduk",
                " Nabu-apla-iddina",
                " Nabu-nadin-zeri",
                " Marduk-zakir-shumi I",
                " Marduk-nadin-ahhe",
                " Simbar-shipak",
                " Shamash-shum-ukin",
                " Baba-aha-iddina",
                " Adad-shuma-usur",
                " Enlil-nadin-shumi",
                " Ninurta-kudurri-usur I",
                " Marduk-ahhe-eriba",
                " Nabu-shuma-ishkunMore"
            ]
        },
        "Neithhotep": {
            "label": "Neithhotep",
            "description": "Neithhotep was the first queen of ancient Egypt, cofounder of the First dynasty, and is the earliest woman in history whose name is known. The name Neithhotep means \"[The Goddess] Neith is satisfied\". Wikipedia",
            "type": "",
            "Children ": [
                "Hor-Aha",
                " Benerib"
            ],
            "People also search for": []
        },
        "Nepotianus": {
            "label": "Nepotianus",
            "description": "Iulius Nepotianus, commonly known in English as Nepotian, was a member of the Constantinian dynasty who reigned as a short-lived usurper of the Roman Empire. Wikipedia",
            "type": "",
            "Died ": [
                "June 30",
                " 350 AD",
                " Rome",
                " Italy"
            ],
            "Parents ": [
                "Virius Nepotianus",
                " Eutropia"
            ],
            "People also search for": []
        },
        "Ordulf, Duke of Saxony": {
            "label": "Ordulf, Duke of Saxony",
            "description": "Ordulf was the duke of Saxony from 1059, when he succeeded his father Bernard II, until his death. He was a member of the Billung family. Wikipedia",
            "type": "",
            "Born ": [
                "1022",
                " Germany"
            ],
            "Died ": "March 28, 1072",
            "Parents ": [
                "Bernard II",
                " Duke of Saxony"
            ],
            "Spouse ": [
                "Gertrude of Haldensleben (m. 1071–1072)",
                " Wulfhild of Norway (m. 1042–1071)"
            ],
            "Children ": [
                "Magnus",
                " Duke of Saxony"
            ],
            "People also search for": []
        },
        "Otto II, Duke of Swabia": {
            "label": "Otto II, Duke of Swabia",
            "description": "Otto II was Count Palatine of Lotharingia, then Duke of Swabia, and all the while Count in Deutz and Auelgau. He was the son of Ezzo and Matilda, and a member of the Ezzonian dynasty. Wikipedia",
            "type": "",
            "Died ": [
                "1047"
            ],
            "Children ": [
                "Richenza of Swabia"
            ],
            "Parents ": [
                "Matilda of Germany",
                " Ezzo",
                " Count Palatine of Lotharingia"
            ],
            "People also search for ": [
                "Ezzo",
                " Count Palatine of Lotharingia",
                " Herman I",
                " Count Palatine of Lotharingia",
                " Richenza of Swabia",
                " Richeza of Lotharingia",
                " Herman II",
                " Matilda of Germany",
                " Liudolf of Lotharingia",
                " Erenfried II",
                " Otto of Nordheim",
                " Henry I",
                " Count Palatine of Lotharingia",
                " Hermann II",
                " Count Palatine of Lotharingia",
                " Ernest II",
                " Duke of Swabia",
                " Herman IV",
                " Duke of Swabia",
                " Frederick I",
                " Duke of Swabia",
                " Otto I",
                " Duke of Swabia and Bavaria",
                " Conrad I",
                " Duke of Swabia",
                " Liudolf",
                " Duke of Swabia",
                " Herman II",
                " Duke of Swabia",
                " Berthold II",
                " Duke of Swabia",
                " Helena Sverkersdotter of SwedenMore"
            ]
        },
        "Prince Marko": {
            "label": "Prince Marko",
            "description": "Marko Mrnjavčević was the de jure Serbian king from 1371 to 1395 and the de facto ruler of territory in western Macedonia centered on the town of Prilep. Wikipedia",
            "type": "",
            "Born ": [
                "1335",
                " Livno",
                " Bosnia and Herzegovina"
            ],
            "Died ": "May 17, 1395, Wallachia, Romania",
            "Spouse ": [
                "Jelena Hlapen"
            ],
            "Parents ": [
                "Vukašin Mrnjavčević",
                " Jelena Mrnjavčević"
            ],
            "People also search for": []
        },
        "Prince Georg of Bavaria": {
            "label": "Prince Georg of Bavaria",
            "description": "Prince Georg of Bavaria was a member of the Bavarian Royal House of Wittelsbach and a Catholic priest. Wikipedia",
            "type": "",
            "Born ": "April 2, 1880, Munich, Germany",
            "Died ": "May 31, 1943, Rome, Italy",
            "Spouse ": [
                "Archduchess Isabella of Austria"
            ],
            "Parents ": [
                "Archduchess Gisela of Austria",
                " Prince Leopold of Bavaria"
            ],
            "People also search for": []
        },
        "Regalianus": {
            "label": "Regalianus",
            "description": "P. C Regalianus was a Dacian general who turned against the Roman Empire and became himself emperor for a brief period, being murdered by the hands who raised him to power. Wikipedia",
            "type": "",
            "Died ": [
                "260 AD",
                " Carnuntum",
                " Austria"
            ],
            "Spouse ": [
                "Sulpicia Dryantilla"
            ],
            "People also search for": []
        },
        "Ricberht of East Anglia": {
            "label": "Ricberht of East Anglia",
            "description": "Ricberht, may have briefly ruled East Anglia, a small independent Anglo-Saxon kingdom which today includes the English counties of Norfolk and Suffolk. Little is known of his life or his reign. Wikipedia",
            "type": "",
            "Parents ": [
                "Rædwald of East Anglia"
            ],
            "People also search for ": [
                "Eorpwald of East Anglia",
                " Rædwald of East Anglia",
                " Sigeberht of East Anglia",
                " Æthelhere of East Anglia",
                " Æthelwold of East Anglia",
                " Eni of East Anglia",
                " Ecgric of East Anglia",
                " Ælfwald of East Anglia",
                " Ealdwulf of East Anglia",
                " Tytila of East Anglia",
                " Wuffa of East Anglia",
                " Wehha of East Anglia",
                " Æthelburh of Faremoutiers",
                " Eadwald of East Anglia",
                " Sæthryth",
                " Alberht of East Anglia",
                " Anna of East Anglia",
                " Guthrum II",
                " Beonna of East Anglia",
                " Eohric of East AngliaMore"
            ]
        },
        "Robert de Brus, 5th Lord of Annandale": {
            "label": "Robert de Brus, 5th Lord of Annandale",
            "description": "Robert V de Brus, 5th Lord of Annandale, was a feudal lord, Justice and Constable of Scotland and England, a Regent of Scotland, and a leading competitor for the Scottish throne in 1290/92 in the Great Cause. Wikipedia",
            "type": "",
            "Born ": [
                "1215"
            ],
            "Died ": "March 31, 1295, Lochmaben Castle, United Kingdom",
            "Children ": [
                "Robert de Brus",
                " 6th Lord of Annandale",
                " Isabel",
                " daughter of Robert Bruce 5th Lord of Annandale",
                " Constance",
                " daughter of Robert Bruce",
                " 5th Lord of AnnandaleMore"
            ],
            "Parents ": [
                "Isobel of Huntingdon",
                " Robert de Brus",
                " 4th Lord of Annandale"
            ],
            "People also search for": []
        },
        "Ruaidrí Ua Conchobair": {
            "label": "Rory O'Connor",
            "description": "Ruaidrí Ua Conchobair was King of Connacht from 1156 to 1186, and from 1166 to 1183 was the last High King of Ireland before the Norman invasion.\nRuaidrí was one of over twenty sons of King Tairrdelbach Ua Conchobair. Wikipedia",
            "type": "",
            "Born ": [
                "1116"
            ],
            "Died ": [
                "1198",
                " Cong Abbey",
                " Cong",
                " Republic of Ireland"
            ],
            "Parents ": [
                "Tairrdelbach Ua Conchobair"
            ],
            "Previous office ": [
                "High King of Ireland (1166–1186)"
            ],
            "Children ": [
                "Conchobar Maenmaige Ua Conchobair"
            ],
            "Siblings ": [
                "Cathal Crobhdearg Ua Conchobair"
            ],
            "People also search for ": [
                "Tairrdelbach Ua Conchobair",
                " Cathal Crobhdearg Ua Conchobair",
                " Diarmait Mac Murchada",
                " Muirchertach Mac Lochlainn",
                " Muirchertach Ua Briain",
                " Tigernán Ua Ruairc",
                " Máel Sechnaill mac Domnaill",
                " Richard de Clare",
                " 2nd Earl of Pembroke",
                " Conchobar Maenmaige Ua Conchobair",
                " Donnchad mac Briain",
                " Domnall Ua Lochlainn",
                " Máel Sechnaill mac Máele Ruanaid",
                " Toirdelbach Ua Briain",
                " Edward Bruce",
                " Aoife MacMurrough",
                " Hugh de Lacy",
                " Lord of Meath",
                " Ruaidrí na Saide Buide",
                " Robert FitzStephen",
                " Áed Findliath mac Neíll",
                " Fedlim Ó ConchobairMore"
            ],
            "See results about": []
        },
        "Rudolf Christian, Count of East Frisia": {
            "label": "Rudolf Christian, Count of East Frisia",
            "description": "Rudolf Christian of Ostfriesland, Count of East Frisia, was count of East Frisia, and the second son of Enno III of East Frisia and Anna of Holstein-Gottorp. Wikipedia",
            "type": "",
            "Born ": "June 2, 1602, Hage, Germany",
            "Died ": "April 17, 1628, Hage, Germany",
            "Parents ": [
                "Anna of Holstein-Gottorp",
                " Enno III",
                " Count of East Frisia"
            ],
            "People also search for": []
        },
        "Sālote Tupou III": {
            "label": "Sālote Tupou III",
            "description": "Sālote Mafile‘o Pilolevu Tupou III, GCMG, GCVO, GBE, DStJ, but usually named only Sālote, was queen regnant of Tonga from 5 April 1918 to her death in 1965. Wikipedia",
            "type": "",
            "Born ": "March 13, 1900, Tonga",
            "Died ": "December 16, 1965, Auckland, New Zealand",
            "Spouse ": [
                "Viliami Tungī Mailefihi (m. 1917–1941)"
            ],
            "Parents ": [
                "George Tupou II"
            ],
            "Previous office ": [
                "Queen regnant (1918–1965)"
            ],
            "Children ": [
                "Tāufaʻāhau Tupou IV",
                " Fatafehi Tu'ipelehake"
            ],
            "People also search for": []
        },
        "Sa'id of Egypt": {
            "label": "Sa'id of Egypt",
            "description": "Muhammad Sa'id Pasha was the Wāli of Egypt and Sudan from 1854 until 1863, officially owing fealty to the Ottoman Sultan but in practice exercising virtual independence. He was the fourth son of Muhammad Ali Pasha. Wikipedia",
            "type": "",
            "Born ": "March 17, 1822, Cairo, Egypt",
            "Died ": "January 18, 1863, Cairo, Egypt",
            "Parents ": [
                "Muhammad Ali of Egypt"
            ],
            "People also search for": []
        },
        "Sabinianus": {
            "label": "Sabinianus",
            "description": "Sabinianus was the leader of a revolt against Gordian III in Africa. He proclaimed himself Emperor, but after being defeated by the governor of Mauretania, his supporters in Carthage surrendered him to the imperial authorities. Wikipedia",
            "type": "",
            "People also search for": []
        },
        "Sartaq Khan": {
            "label": "Sartaq Khan",
            "description": "Sartaq Khan was the son of Batu Khan and Regent Dowager Khatun Boraqcin of Alchi Tatar. Sartaq succeeded Batu as khan of the Ulus of Jochi.\nIn 1252, Alexander Nevsky met with Sartaq at Sarai. Wikipedia",
            "type": "",
            "Died ": [
                "1256"
            ],
            "Parents ": [
                "Batu Khan"
            ],
            "Children ": [
                "Ulaghchi",
                " Theodora",
                " daughter of Sartaq Khan"
            ],
            "People also search for": []
        },
        "Safdarjung": {
            "label": "Safdarjung",
            "description": "Safdar Jung was the Subadar Nawab of Oudh from 19 March 1739 to 5 October 1754. Wikipedia",
            "type": "",
            "Born ": [
                "1708",
                " Nishapur",
                " Iran"
            ],
            "Died ": "October 5, 1754, Sultanpur, Uttar Pradesh, India",
            "Children ": [
                "Shuja-ud-Daula"
            ],
            "People also search for": []
        },
        "Shammuramat": {
            "label": "Shammuramat",
            "description": "Shammuramat or Sammu-ramat was a Queen of Assyria between 811 and 808 BCE. Wikipedia",
            "type": "",
            "Spouse ": [
                "Shamshi-Adad V"
            ],
            "Children ": [
                "Adad-nirari III"
            ],
            "People also search for ": [
                "Shamshi-Adad V",
                " Adad-nirari III",
                " Ctesias",
                " Ara the Beautiful"
            ]
        },
        "Shu-Ilishu": {
            "label": "Shu-Ilishu",
            "description": "Šu-ilišu, ca. 1920 BC – 1911 BC, or 1984- 1975 BC was the 2nd ruler of the 1st Dynasty of Isin and reigned for 10 years according to his extant year-names and a single copy of the Sumerian King List, ... Wikipedia",
            "type": "",
            "People also search for ": [
                "Iddin-Dagan",
                " Ur-Ninurta",
                " Ishbi-Erra",
                " Ishme-Dagan",
                " Lipit-Enlil",
                " Bur-Suen",
                " Suen-magir",
                " Damiq-ilishu",
                " Gungunum",
                " Erra-imitti",
                " Ur-du-kuga",
                " Zambiya",
                " Iter-pisha",
                " Enlil-bani",
                " Abisare",
                " Warad-Sin",
                " Sumuel",
                " Lipit-Ishtar",
                " Zabaia",
                " Sin-IddinamMore"
            ]
        },
        "Stephen III of Moldavia": {
            "label": "Stephen III of Moldavia",
            "description": "Stephen III of Moldavia was Prince of Moldavia between 1457 and 1504 and the most prominent representative of the House of Mușat. Wikipedia",
            "type": "",
            "Born ": [
                "1433",
                " Bacău County",
                " Nord-Est",
                " Romania"
            ],
            "Died ": "July 2, 1504, Suceava, Romania",
            "Children ": [
                "Peter IV Rareș"
            ],
            "Spouse ": [
                "Maria Vochița (m. 1478–1504)",
                " Maria din Mangop (m. 1472–1477)",
                " Evdokia Olelkovici (m. 1463–1467)"
            ],
            "Parents ": [
                "Bogdan II of Moldavia",
                " Lady Oltea"
            ],
            "People also search for": []
        },
        "Skandagupta": {
            "label": "Skandagupta",
            "description": "Skandagupta was a Gupta Emperor of northern India. He is generally considered the last of the great Gupta Emperors. Wikipedia",
            "type": "",
            "Died ": [
                "467 AD"
            ],
            "Siblings ": [
                "Purugupta"
            ],
            "People also search for": []
        },
        "Stephen Uroš V of Serbia": {
            "label": "Stephen Uroš V of Serbia",
            "description": "Saint Stephen Uroš V, also known as Stefan Uroš the Weak, was king of the Serbian Empire as co-regent of his father Stefan Uroš IV Dušan Silni and then Emperor. Wikipedia",
            "type": "",
            "Born ": [
                "1336"
            ],
            "Died ": "December 4, 1371",
            "Parents ": [
                "Stephen Uroš IV Dušan of Serbia",
                " Helena of Bulgaria"
            ],
            "People also search for": []
        },
        "Suen-magir": {
            "label": "Suen-magir",
            "description": "Sîn-māgir, inscribed dEN.ZU-ma-gir, “Sîn upholds,” ca. 1763 – 1753 BC or ca. 1827 – 1817 BC was the 14th king of Isin and he reigned for 11 years. Wikipedia",
            "type": "",
            "People also search for ": [
                "Damiq-ilishu",
                " Lipit-Enlil",
                " Bur-Suen",
                " Ur-Ninurta",
                " Shu-Ilishu",
                " Ishme-Dagan",
                " Ur-du-kuga",
                " Iddin-Dagan",
                " Warad-Sin",
                " Iter-pisha",
                " Erra-imitti",
                " Sumuel",
                " Ishbi-Erra",
                " Apil-Sin",
                " Enlil-bani",
                " Gungunum",
                " Abisare",
                " Sin-Iddinam",
                " Rim-Sin I",
                " Nur-AdadMore"
            ]
        },
        "Suleiman I of Persia": {
            "label": "Suleiman I of Persia",
            "description": "Suleiman I was a Safavid shah of Persia who reigned between 1666 and 1694. He was the elder son of the previous shah Abbas II and a Circassian slave, Nakihat Khanum. Wikipedia",
            "type": "",
            "Died ": "July 29, 1694, Isfahan, Iran",
            "Parents ": [
                "Abbas II of Persia"
            ],
            "Children ": [
                "Sultan Husayn"
            ],
            "People also search for": []
        },
        "Svante Nilsson (regent of Sweden)": {
            "label": "Svante Nilsson",
            "description": "Svante Nilsson was a Swedish statesman and regent of Sweden 1504 – 2 January 1512. Wikipedia",
            "type": "",
            "Born ": [
                "1460"
            ],
            "Died ": "January 2, 1512",
            "Spouse ": [
                "Mette Dyre (m. 1504–1512)"
            ],
            "Children ": [
                "Sten Sture the Younger"
            ],
            "People also search for": []
        },
        "Taejo of Joseon": {
            "label": "Taejo of Joseon",
            "description": "Taejo of Joseon, born Yi Seong-gye, whose changed name is Yi Dan, was the founder and the first king of the Joseon Dynasty of Korea, and the main figure in overthrowing the Goryeo Dynasty. Wikipedia",
            "type": "",
            "Born ": "October 11, 1335, Hamhung, North Korea",
            "Died ": [
                "1408",
                " Changdeokgung",
                " South Korea"
            ],
            "Parents ": [
                "Yi Jachun"
            ],
            "Children ": [
                "Taejong of Joseon",
                " Jeongjong of Joseon",
                " Prince Jinan"
            ],
            "People also search for": []
        },
        "Tahmasp I": {
            "label": "Tahmasp I",
            "description": "Tahmasp I was an influential Shah of Iran, who enjoyed the longest reign of any member of the Safavid dynasty. He was the son and successor of Ismail I. Wikipedia",
            "type": "",
            "Born ": "February 22, 1514, Isfahan, Iran",
            "Died ": "May 14, 1576, Qazvin, Iran",
            "Parents ": [
                "Shah-Begi Khanum",
                " Ismail I"
            ],
            "Spouse ": [
                "Zahra Baji",
                " Aisha Begum",
                " Huri-Khan Khanum",
                " Khan-Parwar Khanum",
                " Zainab Sultan Khanum",
                " Kadamali Sultan Begum",
                " Sultanzada Khanum",
                " Sultan Agha KhanumMore"
            ],
            "Siblings ": [
                "Prince ‘Abul Ghazi Sultan Alqas Mirza",
                " Princess Pari Khan Khanum",
                " Prince ‘Abul Naser Sultan Sam Mirza",
                " Princess Shah Zainab Khanum",
                " Princess Fulaneh Begum",
                " Princess Mahin Banu Khanum",
                " Princess Gunish Khanum",
                " Princess Khair un-nisa Khanish Khanum",
                " Prince ‘Abu'l Fat'h Sultan Moez od-din Bahram Mirza",
                " Prince Soltan Hossein Mirza",
                " Prince Sultan Rustam Mirza",
                " Princess Farangis KhanumMore"
            ],
            "Children ": [
                "Ismail II",
                " Mohammad Khodabanda",
                " Haydar Mirza",
                " Pari Khan Khanum",
                " Princess Shahzadi Alamiyan Shahbanu Khanum",
                " Princess Shahzadi Alamiyan Zainab Beygom",
                " Prince Shahzadeh Sultan Murad Mirza",
                " Prince Shahzadeh Musa Mirza",
                " Prince Shahzadeh Sultan Ahmad Mirza",
                " Princess Shahzadi Alamiyan Fatemeh Sultan Beygom",
                " Prince Shahzadeh Zeinal Abedin Mirza",
                " Prince Shahzadeh Sultan Mahmud Mirza",
                " Princess Shahzadi Alamiyan Mariam Sultan Beygom",
                " Princess Shahzadi Alamiyan Beygom Khanoum",
                " Prince Shahzadeh Sultan ‘Ali Quli Mirza",
                " Prince Shahzadeh Sultan Mostafa Mirza",
                " Princess Shahzadi Alamiyan Khanish Begom",
                " Princess Shahzadeh Alamiyan Gowhar Sultan Beygom",
                " Prince Shahzadeh Sultan Soleiman Mirza",
                " Princess Shahzadi Alamiyan Khadija Sultan Begum",
                " Prince Shahzadeh Imam Qoli Mirza",
                " Prince Shahzadeh Sultan ‘Ali MirzaMore"
            ],
            "People also search for": []
        },
        "Tervel of Bulgaria": {
            "label": "Tervel of Bulgaria",
            "description": "Khan Tervel also called Tarvel, or Terval, or Terbelis in some Byzantine sources, was the Emperor of the Bulgarians at the beginning of the 8th century. In 705 Emperor Justinian II named him Caesar, the first foreigner to receive this title. Wikipedia",
            "type": "",
            "Parents ": [
                "Asparukh of Bulgaria"
            ],
            "Children ": [
                "Telerig of Bulgaria"
            ],
            "People also search for": []
        },
        "Tahmasp II": {
            "label": "Tahmasp II",
            "description": "Tahmasp II or Tahmasebi II was one of the last Safavid rulers of Persia. Tahmasp was the son of Sultan Husayn, the Shah of Iran at that time. When Husayn was forced to abdicate by the Afghans in 1722, Prince Tahmasp wished to claim the throne. Wikipedia",
            "type": "",
            "Born ": [
                "1704"
            ],
            "Died ": [
                "1740",
                " Sabzevar",
                " Iran"
            ],
            "Parents ": [
                "Sultan Husayn"
            ],
            "Children ": [
                "Abbas III"
            ],
            "People also search for": []
        },
        "Theophilos (king)": {
            "label": "Theophilos",
            "description": "Theophilos was a minor Indo-Greek king who ruled for a short time in the Paropamisadae. He was possibly a relative of Zoilos I and is only known from coins. Wikipedia",
            "type": "",
            "People also search for ": [
                "Zoilos II",
                " Diomedes Soter",
                " Polyxenos Epiphanes Soter",
                " Philoxenus Anicetus",
                " King Telephos",
                " Lysias Anicetus",
                " Dionysios Soter",
                " Zoilos I",
                " Heliokles II",
                " Antimachus II",
                " Strato I",
                " Demetrios III",
                " Archebius",
                " Peukolaos",
                " King Nicias",
                " Amyntas Nikator",
                " Agathokleia",
                " Antialcidas",
                " Epander",
                " ApollophanesMore"
            ]
        },
        "Thurisind": {
            "label": "Thurisind",
            "description": "Thurisind was king of the Gepids, an East Germanic Gothic people, from c. 548 to 560. He was the penultimate Gepid king, and succeeded King Elemund by staging a coup d'état and forcing the king's son into exile. Wikipedia",
            "type": "",
            "Children ": [
                "Cunimund",
                " Turismod"
            ],
            "People also search for ": [
                "Audoin",
                " Cunimund",
                " Turismod",
                " Elemund",
                " Alboin",
                " Rosamund",
                " Wacho",
                " Ardaric",
                " Walthari",
                " Liutprand",
                " King of the Lombards",
                " HelmichisMore"
            ]
        },
        "Tiglath-Pileser I": {
            "label": "Tiglath-Pileser I",
            "description": "Tiglath-Pileser I was a king of Assyria during the Middle Assyrian period. According to Georges Roux, Tiglath-Pileser was \"one of the two or three great Assyrian monarchs since the days of Shamshi-Adad I\". Wikipedia",
            "type": "",
            "Died ": [
                "1076"
            ],
            "Parents ": [
                "Ashur-resh-ishi I"
            ],
            "Children ": [
                "Ashur-bel-kala"
            ],
            "People also search for": []
        },
        "Ur-Ninurta": {
            "label": "Ur-Ninurta",
            "description": "Ur-Ninurta, ca. 1859 – 1832 BC or ca. 1923 – 1896 BC, was the 6th king of the 1st Dynasty of Isin. A usurper, Ur-Ninurta seized the throne on the fall of Lipit-Ištar and held it until his violent death some 28 years later. Wikipedia",
            "type": "",
            "People also search for ": [
                "Lipit-Enlil",
                " Iddin-Dagan",
                " Bur-Suen",
                " Ishme-Dagan",
                " Shu-Ilishu",
                " Gungunum",
                " Suen-magir",
                " Ishbi-Erra",
                " Damiq-ilishu",
                " Abisare",
                " Erra-imitti",
                " Sumuel",
                " Lipit-Ishtar",
                " Ur-du-kuga",
                " Enlil-bani",
                " Warad-Sin",
                " Zabaia",
                " Iter-pisha",
                " Nur-Adad",
                " Sin-IddinamMore"
            ]
        },
        "Vima Takto": {
            "label": "Vima Takto",
            "description": "Vima Takto or Vima Taktu was a Kushan emperor reigned c. 80–90 CE. Wikipedia",
            "type": "",
            "Children ": [
                "Vima Kadphises"
            ],
            "People also search for": []
        },
        "Mutara II Rwogera": {
            "label": "Mutara II Rwogera",
            "description": "Mutara II Rwogera was the King of Rwanda from 1830 to 1853. Wikipedia",
            "type": "",
            "Born ": [
                "1802"
            ],
            "Died ": [
                "1853"
            ],
            "People also search for": []
        },
        "Toktu of Bulgaria": {
            "label": "Toktu of Bulgaria",
            "description": "Toktu was the ruler of Bulgaria between 766–767.\nThe Byzantine chronicler Patriarch Nikephoros records that Toktu was \"a Bulgarian, and a brother of Bayan\". Wikipedia",
            "type": "",
            "Died ": [
                "767 AD"
            ],
            "Children ": [
                "Krum"
            ],
            "People also search for": []
        },
        "Edzard II, Count of East Frisia": {
            "label": "Edzard II, Count of East Frisia",
            "description": "Edzard II, Count of East Frisia was count of East Frisia, and the son of Enno II of East Frisia and Anna of Oldenburg.\nDuring his reign, he came into conflict with the city of Emden. Wikipedia",
            "type": "",
            "Born ": "June 24, 1532, Greetsiel, Germany",
            "Died ": "March 1, 1599, Aurich, Germany",
            "Spouse ": [
                "Catherine Vasa"
            ],
            "Children ": [
                "Enno III",
                " Count of East Frisia",
                " John III of Rietberg"
            ],
            "Parents ": [
                "Enno II",
                " Count of East Frisia",
                " Anna of Oldenburg"
            ],
            "People also search for": []
        }
    },
    "summary": {
        "label": 95,
        "description": 95,
        "type": 95,
        "died": 1,
        "children": 1,
        "people_also_search_for": 1,
        "parents": 1,
        "siblings": 1,
        "born": 1,
        "spouse": 1,
        "full_name": 1,
        "assassinated": 1,
        "structures": 1,
        "education": 1,
        "see_results_about": 1,
        "previous_office": 1
    },
    "infoboxless": [
        "Akbar Khan",
        "Amanibakhi",
        "Boris II of Bulgaria",
        "Pagan of Bulgaria",
        "Ur-du-kuga"
    ]
}